{
  "badges": [
    "Licensed in the UAE",
    "1000+ Clients Served"
  ],
  "title": "Invest Smarter with Data-Driven High Returns UAE Real Estate Program",
  "subtitle": "Forever Estates helps investors achieve stronger returns through rigorous analysis, transparent advisory, and end-to-end support at zero cost.",
  "cta": {
    "text": "Schedule your FREE consultation",
    "contacts": {
      "text": "Or call us",
      "links": [
        "+971-50-386-4952",
        "Start Conversation"
      ]
    }
  }
}
